{
  "id": "what_is_a_90_degree_release",
  "source": "Expert Patch",
  "organization": "",
  "question": "What is a “90-degree” release?",
  "content": "A 90‑degree release means the ball is coming off your hand with maximum axis rotation, the ball is spinning almost completely sideways relative to your target line.\nThink of it like this:\nIf 0° = pure forward roll\nAnd 45° = a balanced blend of forward + side roll\nThen 90° = almost pure side roll\nAt 90°, your fingers rotate around the side of the ball so much that the ball’s axis is nearly horizontal to the lane.\nA 90 degree release creates:\nMaximum skid in the front\nVery late hook\nVery sharp backend angle\nHigh entry angle potential\nHigh risk of over/under if the lane doesn’t have friction downlane\nIt’s the most angular release you can make."
}