{
  "id": "what_is_5_and_3",
  "source": "Expert Patch",
  "organization": "",
  "question": "what is 5 and 3?",
  "content": "“5 and 3” is a more aggressive version of parallel-style adjustments like 2 and 1 or 3 and 2.\n\nThe bowler moves their feet five boards and their target three boards in the same direction.\n\nIt’s commonly used when lane transition, increased friction, or ball reaction forces you to move inside and push the breakpoint deeper down the lane. This adjustment allows you to change angle and breakpoint position while keeping the same speed, release, and physical execution."
}