{
  "id": "where_do_i_place_myself_on_the_lane",
  "source": "Expert Patch",
  "organization": "",
  "question": "WHERE do i PLACE MYSELF ON THE LANE?",
  "content": "Most of the time, the best answer is actually where not to play.\n You want to avoid parts of the lane where you can’t miss without getting punished.\n Choose a spot where:\n \n there is friction outside your target,\n there is more oil inside your target,\n and you have some room to miss without losing the pocket.\n \n Stay away from \"penalty zones\", areas that hook too early or never hook at all.\n Pay attention to what the other bowlers are doing, because their shots will change the lane, especially around the breakpoint (carrydown) and the front of the lane (transition).\n If you can keep friction outside and oil inside, your ball will react predictably and you’ll stay in control."
}